.hgignore
.hgtags
.readthedocs.yml
AUTHORS.rst
CHANGES.rst
LICENSE.txt
Makefile
README.rst
bitbucket-pipelines.yml
setup.cfg
setup.py
setup_build.py
tox.ini
.ci/deploy_pypi.sh
.ci/install_shtns.sh
.ci/install_shtns_user.sh
doc/Makefile
doc/authors.rst
doc/changes.rst
doc/conf.py
doc/environment.yml
doc/index.rst
doc/install.rst
doc/learn.rst
doc/logo.svg
doc/make.bat
doc/install/VERSIONS.sh
doc/install/install_shtns.sh
doc/install/sht_libs.rst
fluidsht/__init__.py
fluidsht/_version.py
fluidsht/compat.py
fluidsht/util.py
fluidsht.egg-info/PKG-INFO
fluidsht.egg-info/SOURCES.txt
fluidsht.egg-info/dependency_links.txt
fluidsht.egg-info/requires.txt
fluidsht.egg-info/top_level.txt
fluidsht/sht2d/__init__.py
fluidsht/sht2d/_try_compare_shtools_shtns.py
fluidsht/sht2d/_try_with_shtools.py
fluidsht/sht2d/operators.py
fluidsht/sht2d/tests.py
fluidsht/sht2d/with_shtns.py
fluidsht/sht2d/__pythran__/operators.cpp