Metadata-Version: 1.1
Name: fluidsht
Version: 0.0.4a0
Summary: Spherical Harmonics Transform API
Home-page: UNKNOWN
Author: FluidDyn Developers
Author-email: fluiddyn@freelists.org
License: CeCILL License
Keywords: spherical harmonics,shtns,shtools
Platform: UNKNOWN
Classifier: Development Status :: 3 - Alpha
Classifier: Intended Audience :: Science/Research
Classifier: Intended Audience :: Education
Classifier: Topic :: Scientific/Engineering
Classifier: License :: OSI Approved :: GNU General Public License v2 (GPLv2)
Classifier: Programming Language :: Python :: 3
Classifier: Programming Language :: Python :: 3.6
Classifier: Programming Language :: Python :: 3.7
